setup.py
nbt_utils/__init__.py
nbt_utils/tag_ids.py
nbt_utils.egg-info/PKG-INFO
nbt_utils.egg-info/SOURCES.txt
nbt_utils.egg-info/dependency_links.txt
nbt_utils.egg-info/requires.txt
nbt_utils.egg-info/top_level.txt
nbt_utils/tag/__init__.py
nbt_utils/tag/byte_array_tag.py
nbt_utils/tag/byte_tag.py
nbt_utils/tag/compound_tag.py
nbt_utils/tag/double_tag.py
nbt_utils/tag/end_tag.py
nbt_utils/tag/float_tag.py
nbt_utils/tag/int_array_tag.py
nbt_utils/tag/int_tag.py
nbt_utils/tag/list_tag.py
nbt_utils/tag/long_array_tag.py
nbt_utils/tag/long_tag.py
nbt_utils/tag/short_tag.py
nbt_utils/tag/string_tag.py
nbt_utils/utils/__init__.py
nbt_utils/utils/nbt.py
nbt_utils/utils/nbt_be_binary_stream.py
nbt_utils/utils/nbt_le_binary_stream.py
nbt_utils/utils/nbt_net_le_binary_stream.py