Metadata-Version: 1.1
Name: nbt-utils
Version: 1.7
Summary: Podrum's NBT library.
Home-page: https://github.com/Podrum/nbt_utils
Author: Podrum
Author-email: UNKNOWN
License: MIT
Keywords: nbt_utils,nbt,utils,python3
Platform: UNKNOWN
Classifier: Development Status :: 5 - Production/Stable
Classifier: Intended Audience :: Developers
Classifier: Topic :: Software Development :: Libraries
Classifier: License :: OSI Approved :: MIT License
Classifier: Programming Language :: Python :: 3.5
Classifier: Programming Language :: Python :: 3.6
Classifier: Programming Language :: Python :: 3.7
Classifier: Programming Language :: Python :: 3.8
Classifier: Programming Language :: Python :: 3.9
Classifier: Programming Language :: Python :: 3.10
